[
  {
    "name": "Rocio Inmuebles",
    "desc": "Asesora Inmobiliaria",
    "iconurl": "/assets/images/picture.png",
    "links": [
      {
        "name": "WhatsApp",
        "icon": "/assets/icons/whatsapp.svg",
        "url": "https://wa.me/+595973205207?text=Hola%20Rocio!"
      },
      {
        "name": "Facebook",
        "icon": "/assets/svg/facebook.svg",
        "url": "https://www.facebook.com/profile.php?id=100063693392997"
      },
      {
        "name": "Instagram",
        "icon": "/assets/icons/instagram.svg",
        "url": "https://www.instagram.com/rocioinmuebles/"
      }
    ]
  }
]
